README.rst
setup.py
bookends/__init__.py
bookends/bookends.py
bookends/step.py
bookends/stop.py
bookends/stop_as_final_func.py
bookends.egg-info/PKG-INFO
bookends.egg-info/SOURCES.txt
bookends.egg-info/dependency_links.txt
bookends.egg-info/not-zip-safe
bookends.egg-info/top_level.txt