Metadata-Version: 1.0
Name: bookends
Version: 0.0.5
Summary: A simple piping syntax
Home-page: http://github.com/berrytj/bookends
Author: Tom Berry
Author-email: tberry860@gmail.com
License: MIT
Keywords: functional pipe
Platform: UNKNOWN
